rosmobilelib/__init__.py
rosmobilelib/area_globalization.py
rosmobilelib/occupancygrid_utils.py
rosmobilelib/ros_utils.py
rosmobilelib/rosclients.py
rosmobilelib-0.1.2.9.dist-info/WHEEL
rosmobilelib-0.1.2.9.dist-info/METADATA
rosmobilelib-0.1.2.9.dist-info/RECORD
