Metadata-Version: 2.1
Name: rosmobilelib
Version: 0.1.2.9
Summary: rosmobilelib
Home-page: https://github.com/wwwshwww
License: MIT
Author: moyash
Author-email: www.shinderu.www@gmail.com
Requires-Python: >=3.5,<4.0
Classifier: License :: OSI Approved :: MIT License
Classifier: Programming Language :: Python :: 3
Classifier: Programming Language :: Python :: 3.5
Classifier: Programming Language :: Python :: 3.6
Classifier: Programming Language :: Python :: 3.7
Classifier: Programming Language :: Python :: 3.8
Requires-Dist: numpy (>=1.18.4,<2.0.0)
Requires-Dist: numpy-quaternion (==2019.12.11.22.25.52)
Requires-Dist: opencv-python (>=4.0,<5.0)
Requires-Dist: roslibpy (>=1.1.0,<2.0.0)
Requires-Dist: sklearn (>=0.0,<0.1)
Project-URL: Repository, https://github.com/wwwshwww/rosmobilelib
